{
  "stationCollection": [
    {
      "id": "01",
      "name": "Tramore",
      "latitude": "52.1624",
      "longitude": "-7.1524",
      "userid": "3ad52697-6d98-4d80-8273-084de55a86c0",
      "readings": [
        {
          "id": "04",
          "code": 700,
          "temperature": 8,
          "windSpeed": 1,
          "pressure": 1005,
          "windDirection": 101,
          "date": "2021-06-25T07:20:42.138Z",
          "weatherCodeString": "<span class='icon is-large'><i class='fas fa-2x fa-snowflake'></i></span>Snow",
          "tempInF": 46.4,
          "windSpeedInBft": "0 bft",
          "feelsLike": 9.9,
          "windDirectionText": "East"
        },
        {
          "id": "03",
          "code": 600,
          "temperature": 6,
          "windSpeed": 2,
          "pressure": 1004,
          "windDirection": 96,
          "date": "2021-05-25T07:20:42.138Z"
        },
        {
          "id": "02",
          "code": 800,
          "temperature": 0.5,
          "windSpeed": 3.5,
          "pressure": 1002,
          "windDirection": 90,
          "date": "2021-04-25T07:20:42.138Z",
          "weatherCodeString": "<span class='icon is-large'><i class='fas fa-2x fa-bolt'></i></span>Thunder",
          "tempInF": 32.9,
          "windSpeedInBft": "1 bft",
          "feelsLike": -0.2,
          "windDirectionText": "East"
        },
        {
          "id": "ba128370-01fa-11ec-a0be-ab47a6bb5e62",
          "code": 701,
          "temperature": 15.55,
          "windSpeed": 3.13,
          "windDirection": 226,
          "pressure": 1011,
          "date": "2021-08-20T22:08:11.000Z"
        }
      ],
      "minTemp": 0.5,
      "maxTemp": 8,
      "minWindSpeed": 1,
      "maxWindSpeed": 3.5,
      "minPressure": 1002,
      "maxPressure": 1005,
      "temperatureTrend": "<span class='icon is-medium text-right text-error'><i class='fas fa-2x fa-arrow-down'></i></span>",
      "windTrend": "<span class='icon is-medium text-right text-success'><i class='fas fa-2x fa-arrow-up'></i></span>",
      "pressureTrend": "<span class='icon is-medium text-right text-error'><i class='fas fa-2x fa-arrow-down'></i></span>"
    },
    {
      "id": "05",
      "name": "Dunmore",
      "latitude": "41.4198",
      "longitude": "-75.6324",
      "userid": "3ad52697-6d98-4d80-8273-084de55a86c0",
      "readings": [
        {
          "id": "633dc930-01fd-11ec-9afc-cd8110e5fed4",
          "code": 701,
          "temperature": 22.89,
          "windSpeed": 1.54,
          "windDirection": 140,
          "pressure": 1013,
          "date": "2021-08-20T22:27:14.000Z",
          "tempTrend": [
            24.94,
            25.29,
            25.88,
            27.38,
            30.55,
            31.95,
            31.59,
            27.18
          ],
          "trendLabels": [
            "20/7/2021",
            "21/7/2021",
            "22/7/2021",
            "23/7/2021",
            "24/7/2021",
            "25/7/2021",
            "26/7/2021",
            "27/7/2021"
          ],
          "weatherCodeString": "<span class='icon is-large'><i class='fas fa-2x fa-poo-storm'></i></span>Unknown",
          "tempInF": 73.202,
          "windSpeedInBft": "1 bft",
          "feelsLike": 24.9,
          "windDirectionText": "South East"
        },
        {
          "id": "6477f6e0-01fd-11ec-9afc-cd8110e5fed4",
          "code": 701,
          "temperature": 22.89,
          "windSpeed": 1.54,
          "windDirection": 140,
          "pressure": 1013,
          "date": "2021-08-20T22:27:16.000Z",
          "tempTrend": [
            24.94,
            25.29,
            25.88,
            27.38,
            30.55,
            31.95,
            31.59,
            27.18
          ],
          "trendLabels": [
            "20/7/2021",
            "21/7/2021",
            "22/7/2021",
            "23/7/2021",
            "24/7/2021",
            "25/7/2021",
            "26/7/2021",
            "27/7/2021"
          ],
          "weatherCodeString": "<span class='icon is-large'><i class='fas fa-2x fa-poo-storm'></i></span>Unknown",
          "tempInF": 73.202,
          "windSpeedInBft": "1 bft",
          "feelsLike": 24.9,
          "windDirectionText": "South East"
        },
        {
          "id": "07",
          "code": 200,
          "temperature": 0.5,
          "windSpeed": 3.5,
          "pressure": 1000,
          "windDirection": 102,
          "date": "2021-03-25T07:20:42.138Z",
          "weatherCodeString": "<span class='icon is-large'><i class='fas fa-2x fa-cloud-sun'></i></span>Partial Clouds",
          "tempInF": 32.9,
          "windSpeedInBft": "1 bft",
          "feelsLike": -0.2,
          "windDirectionText": "East South East"
        },
        {
          "id": "06",
          "code": 700,
          "temperature": 8,
          "windSpeed": 1,
          "pressure": 999,
          "windDirection": 98,
          "date": "2021-02-25T07:20:42.138Z"
        },
        {
          "id": "e3f969d0-01fd-11ec-98e6-fdc2519ed68b",
          "code": 701,
          "temperature": 22.82,
          "windSpeed": 1.54,
          "windDirection": 140,
          "pressure": 1013,
          "date": "2021-08-20T22:30:50.000Z",
          "tempTrend": [
            25.45,
            25.29,
            25.88,
            27.38,
            30.55,
            31.95,
            31.59,
            27.18
          ],
          "trendLabels": [
            "20/7/2021",
            "21/7/2021",
            "22/7/2021",
            "23/7/2021",
            "24/7/2021",
            "25/7/2021",
            "26/7/2021",
            "27/7/2021"
          ]
        },
        {
          "id": "ed5691b0-01fd-11ec-b66e-072f29e9fc9c",
          "code": 701,
          "temperature": 22.81,
          "windSpeed": 1.54,
          "windDirection": 140,
          "pressure": 1013,
          "date": "2021-08-20T22:31:06.000Z",
          "tempTrend": [
            25.45,
            25.29,
            25.88,
            27.38,
            30.55,
            31.95,
            31.59,
            27.18
          ],
          "trendLabels": [
            "20/7/2021",
            "21/7/2021",
            "22/7/2021",
            "23/7/2021",
            "24/7/2021",
            "25/7/2021",
            "26/7/2021",
            "27/7/2021"
          ]
        }
      ],
      "minTemp": 0.5,
      "maxTemp": 22.89,
      "minWindSpeed": 1,
      "maxWindSpeed": 3.5,
      "minPressure": 999,
      "maxPressure": 1013,
      "temperatureTrend": "<span class='icon is-medium text-right text-primary'><i class='fas fa-2x fa-equals'></i></span>",
      "windTrend": "<span class='icon is-medium text-right text-primary'><i class='fas fa-2x fa-equals'></i></span>",
      "pressureTrend": "<span class='icon is-medium text-right text-primary'><i class='fas fa-2x fa-equals'></i></span>"
    }
  ]
}